AUTHORS
CHANGELOG.txt
DESCRIPTION
LICENSE
MANIFEST.in
README.rst
setup.py
django_nicedit.egg-info/PKG-INFO
django_nicedit.egg-info/SOURCES.txt
django_nicedit.egg-info/dependency_links.txt
django_nicedit.egg-info/requires.txt
django_nicedit.egg-info/top_level.txt
nicedit/__init__.py
nicedit/admin.py
nicedit/forms.py
nicedit/models.py
nicedit/urls.py
nicedit/views.py
nicedit/widgets.py
nicedit/migrations/0001_initial.py
nicedit/migrations/0002_auto__add_niceditimage.py
nicedit/migrations/__init__.py
nicedit/static/admin/css/nicedit.css
nicedit/static/img/niceditoricons.gif
nicedit/static/js/nicedit.js
nicedit/static/js/nicedit.min.js
nicedit/templates/admin/base_site.html
nicedit/tests/__init__.py
nicedit/tests/test_image_upload.py