Metadata-Version: 1.0
Name: django-nicedit
Version: 1.1.1
Summary: Nicedit widget for django with image upload feature.
